LICENSE
MANIFEST.in
README.md
package.json
setup.py
dash_luckysheet/Luckysheet.py
dash_luckysheet/__init__.py
dash_luckysheet/_imports_.py
dash_luckysheet/dash_luckysheet.min.js
dash_luckysheet/dash_luckysheet.min.js.map
dash_luckysheet/metadata.json
dash_luckysheet/package-info.json
dash_luckysheet/utils.py
dash_luckysheet.egg-info/PKG-INFO
dash_luckysheet.egg-info/SOURCES.txt
dash_luckysheet.egg-info/dependency_links.txt
dash_luckysheet.egg-info/top_level.txt
dash_luckysheet/assets/EwaAntH.gif
dash_luckysheet/assets/EwaAntV.gif
dash_luckysheet/assets/__init__.py
dash_luckysheet/assets/dash_luckysheet.css
dash_luckysheet/assets/exceljs.min.js
dash_luckysheet/assets/exceljs.min.js.map
dash_luckysheet/assets/icon_dropCell.png
dash_luckysheet/assets/iconfont.css
dash_luckysheet/assets/loading.gif
dash_luckysheet/assets/luckyexcel.umd.js
dash_luckysheet/assets/luckyexcel.umd.js.map
dash_luckysheet/assets/luckysheet.css
dash_luckysheet/assets/luckysheet.umd.js
dash_luckysheet/assets/luckysheet.umd.js.map
dash_luckysheet/assets/plugin.js
dash_luckysheet/assets/plugins.css
dash_luckysheet/assets/pluginsCss.css
dash_luckysheet/assets/waffle_sprite.png
dash_luckysheet/fonts/fontawesome-webfont.ttf
dash_luckysheet/fonts/fontawesome-webfont.woff
dash_luckysheet/fonts/fontawesome-webfont.woff2