Metadata-Version: 1.1
Name: dash-luckysheet
Version: 0.0.6
Summary: Integrate editable excel like speadsheets into dash
Home-page: UNKNOWN
Author: Viktor Krückl <viktor@krueckl.de>
Author-email: UNKNOWN
License: MIT
Platform: UNKNOWN
Classifier: Framework :: Dash
